poetry_dynamic_metadata/__init__.py
poetry_dynamic_metadata/plugin.py
poetry_dynamic_metadata-0.1.3.dist-info/LICENSE
poetry_dynamic_metadata-0.1.3.dist-info/METADATA
poetry_dynamic_metadata-0.1.3.dist-info/WHEEL
poetry_dynamic_metadata-0.1.3.dist-info/entry_points.txt
poetry_dynamic_metadata-0.1.3.dist-info/RECORD
