Metadata-Version: 2.1
Name: poetry-dynamic-metadata
Version: 0.1.3
Summary: Poetry plugin for dynamically extracting any metadata from python modules, files, etc.
Home-page: https://github.com/stakhovsky/poetry-dynamic-metadata
Author: Egor Stakhovsky
Author-email: y.stakhovsky@gmail.com
Requires-Python: >=3.8,<4.0
Classifier: Development Status :: 3 - Alpha
Classifier: Intended Audience :: Developers
Classifier: Intended Audience :: Information Technology
Classifier: Intended Audience :: System Administrators
Classifier: License :: OSI Approved :: MIT License
Classifier: Operating System :: OS Independent
Classifier: Programming Language :: Python
Classifier: Programming Language :: Python :: 3
Classifier: Programming Language :: Python :: 3.8
Classifier: Programming Language :: Python :: 3.9
Classifier: Programming Language :: Python :: 3.10
Classifier: Programming Language :: Python :: 3.11
Classifier: Programming Language :: Python :: 3
Classifier: Programming Language :: Python :: 3 :: Only
Classifier: Programming Language :: Python :: 3.10
Classifier: Programming Language :: Python :: 3.8
Classifier: Programming Language :: Python :: 3.9
Requires-Dist: poetry (>=1.4.1,<2.0.0)
Project-URL: Documentation, https://github.com/stakhovsky/poetry-dynamic-metadata
